marathi_shabda/__init__.py
marathi_shabda/api.py
marathi_shabda/cli.py
marathi_shabda/exceptions.py
marathi_shabda/models.py
marathi_shabda/data/__init__.py
marathi_shabda/data/dictionary.db
marathi_shabda/dictionary/__init__.py
marathi_shabda/dictionary/adapter.py
marathi_shabda/inference/__init__.py
marathi_shabda/inference/kaal_inference.py
marathi_shabda/inference/pos_inference.py
marathi_shabda/morphology/__init__.py
marathi_shabda/morphology/lemmatizer.py
marathi_shabda/morphology/stem_alternations.py
marathi_shabda/morphology/vibhakti_rules.py
marathi_shabda/normalization/__init__.py
marathi_shabda/normalization/safe_normalizer.py
marathi_shabda/normalization/script_detection.py
marathi_shabda/normalization/transliterator.py
marathi_shabda-0.1.2.dist-info/licenses/LICENSE
marathi_shabda-0.1.2.dist-info/METADATA
marathi_shabda-0.1.2.dist-info/WHEEL
marathi_shabda-0.1.2.dist-info/entry_points.txt
marathi_shabda-0.1.2.dist-info/top_level.txt
marathi_shabda-0.1.2.dist-info/RECORD
