Metadata-Version: 2.4
Name: marathi-shabda
Version: 0.1.2
Summary: Deterministic, offline Marathi word analysis library (shabda = word in Marathi)
Author: Prathmesh Santosh Choudhari, Siddhant Akash Bobde, Vedangi Deepak Deshpande
License: CC-BY-NC-SA-4.0
Project-URL: Homepage, https://github.com/iampratham29/marathi-shabda
Project-URL: Documentation, https://github.com/iampratham29/marathi-shabda#readme
Project-URL: Repository, https://github.com/iampratham29/marathi-shabda
Project-URL: Issues, https://github.com/iampratham29/marathi-shabda/issues
Keywords: marathi,nlp,morphology,dictionary,devanagari,lemmatization
Classifier: Development Status :: 3 - Alpha
Classifier: Intended Audience :: Developers
Classifier: Intended Audience :: Education
Classifier: Intended Audience :: Science/Research
Classifier: License :: Free For Educational Use
Classifier: License :: Other/Proprietary License
Classifier: Natural Language :: Marathi
Classifier: Operating System :: OS Independent
Classifier: Programming Language :: Python :: 3
Classifier: Programming Language :: Python :: 3.8
Classifier: Programming Language :: Python :: 3.9
Classifier: Programming Language :: Python :: 3.10
Classifier: Programming Language :: Python :: 3.11
Classifier: Programming Language :: Python :: 3.12
Classifier: Topic :: Text Processing :: Linguistic
Classifier: Topic :: Software Development :: Libraries :: Python Modules
Requires-Python: >=3.8
License-File: LICENSE
Provides-Extra: dev
Requires-Dist: pytest>=7.0; extra == "dev"
Requires-Dist: pytest-cov>=4.0; extra == "dev"
Requires-Dist: ruff>=0.1.0; extra == "dev"
Requires-Dist: mypy>=1.0; extra == "dev"
Requires-Dist: build>=0.10; extra == "dev"
Dynamic: license-file
